general_q/__init__.py
general_q/agents/__init__.py
general_q/agents/base.py
general_q/agents/general_q.py
general_q/agents/names.txt
general_q/agents/replay_memory.py
general_q/decoders/base.py
general_q/encoders/__init__.py
general_q/encoders/auto_encoder.py
general_q/encoders/base.py
general_q/encoders/box_encoder.py
general_q/encoders/composite_encoders.py
general_q/encoders/discrete_encoders.py
general_q/encoders/image_encoder.py
general_q/encoders/tensor_encoder.py
general_q/utils.py
general_q-0.1.0.dist-info/LICENSE
general_q-0.1.0.dist-info/WHEEL
general_q-0.1.0.dist-info/METADATA
general_q-0.1.0.dist-info/RECORD
