Metadata-Version: 2.1
Name: general-q
Version: 0.1.0
Summary: An easy to use library for general purpose reinforcement learning and experimentation
Home-page: https://github.com/khoda81/general_q
License: MIT
Author: axiom
Author-email: 20.mahdikh.0@gmail.com
Requires-Python: >=3.9,<4.0
Classifier: Development Status :: 3 - Alpha
Classifier: Intended Audience :: Developers
Classifier: License :: OSI Approved :: MIT License
Classifier: Operating System :: OS Independent
Classifier: Programming Language :: Python :: 3
Classifier: Programming Language :: Python :: 3.9
Classifier: Programming Language :: Python :: 3.10
Classifier: Programming Language :: Python :: 3
Classifier: Programming Language :: Python :: 3.9
Classifier: Topic :: Software Development :: Libraries :: Python Modules
Project-URL: Repository, https://github.com/khoda81/general_q
